{
  "pair": "USDT/CNY",
  "bid": 6.86835971,
  "ask": 6.95729577,
  "mid": 6.91282774,
  "asof_ts": 1775331422,
  "asof_iso": "2026-04-04T19:37:02Z",
  "timezone": "UTC",
  "source": "okx_p2p",
  "bid_source": "okx_p2p",
  "ask_source": "okx_p2p",
  "source_pool": [
    "okx_p2p"
  ],
  "source_count": 1,
  "sample_count": 139,
  "sample_count_bid": 139,
  "sample_count_ask": 142,
  "dispersion": 0.00289353,
  "dispersion_bid": 0.00152057,
  "dispersion_ask": 0.00426649,
  "quality_score": 94.2,
  "quality_score_bid": 94.4,
  "quality_score_ask": 94.0,
  "calc_version": "rt_v4_bidask",
  "input_hash": "d11b7cdd36015b777762087cf6380da795fc8ead06065e6c8abe2cbd2e3f8733",
  "generated_at": "2026-04-04T19:37:02Z"
}
