{
  "pair": "USDT/CNY",
  "bid": 6.82655405,
  "ask": 6.90939189,
  "mid": 6.86797297,
  "asof_ts": 1775686123,
  "asof_iso": "2026-04-08T22:08:43Z",
  "timezone": "UTC",
  "source": "okx_p2p",
  "bid_source": "okx_p2p",
  "ask_source": "okx_p2p",
  "source_pool": [
    "okx_p2p"
  ],
  "source_count": 1,
  "sample_count": 148,
  "sample_count_bid": 148,
  "sample_count_ask": 148,
  "dispersion": 0.00290214,
  "dispersion_bid": 0.00187387,
  "dispersion_ask": 0.0039304,
  "quality_score": 94.9,
  "quality_score_bid": 95.1,
  "quality_score_ask": 94.7,
  "calc_version": "rt_v4_bidask",
  "input_hash": "aae62ad0c800845ec94821b448b7002250cc1240fcc70d64cc3a09476b235db7",
  "generated_at": "2026-04-08T22:08:43Z"
}
