{
  "pair": "USDT/CNY",
  "bid": 6.91851034,
  "ask": 6.94805517,
  "mid": 6.93328276,
  "asof_ts": 1773658963,
  "asof_iso": "2026-03-16T11:02:43Z",
  "timezone": "UTC",
  "source": "okx_p2p",
  "bid_source": "okx_p2p",
  "ask_source": "okx_p2p",
  "source_pool": [
    "okx_p2p"
  ],
  "source_count": 1,
  "sample_count": 145,
  "sample_count_bid": 145,
  "sample_count_ask": 145,
  "dispersion": 0.00070757,
  "dispersion_bid": 0.00062443,
  "dispersion_ask": 0.00079071,
  "quality_score": 95.1,
  "quality_score_bid": 95.1,
  "quality_score_ask": 95.2,
  "calc_version": "rt_v4_bidask",
  "input_hash": "5301fadcb4f4d003139561feb6ba7fe9a62f3d26227a40ff16553f78dc80f1cb",
  "generated_at": "2026-03-16T11:02:43Z"
}
