{
  "pair": "USDT/CNY",
  "bid": 6.98,
  "ask": 7.00183673,
  "mid": 6.99091837,
  "asof_ts": 1774258747,
  "asof_iso": "2026-03-23T09:39:07Z",
  "timezone": "UTC",
  "source": "okx_p2p",
  "bid_source": "okx_p2p",
  "ask_source": "okx_p2p",
  "source_pool": [
    "okx_p2p"
  ],
  "source_count": 1,
  "sample_count": 145,
  "sample_count_bid": 145,
  "sample_count_ask": 147,
  "dispersion": 0.00041323,
  "dispersion_bid": 0.0,
  "dispersion_ask": 0.00082646,
  "quality_score": 95.2,
  "quality_score_bid": 95.2,
  "quality_score_ask": 95.3,
  "calc_version": "rt_v4_bidask",
  "input_hash": "0caeec50c8d2bdb59b2eaa9dabda985975ae8460dcdf2c948375b57394517ca5",
  "generated_at": "2026-03-23T09:39:07Z"
}
