{
  "pair": "USDT/CNY",
  "bid": 6.94865306,
  "ask": 6.97078621,
  "mid": 6.95971963,
  "asof_ts": 1774175775,
  "asof_iso": "2026-03-22T10:36:15Z",
  "timezone": "UTC",
  "source": "okx_p2p",
  "bid_source": "okx_p2p",
  "ask_source": "okx_p2p",
  "source_pool": [
    "okx_p2p"
  ],
  "source_count": 1,
  "sample_count": 145,
  "sample_count_bid": 147,
  "sample_count_ask": 145,
  "dispersion": 0.00067936,
  "dispersion_bid": 0.00060047,
  "dispersion_ask": 0.00075826,
  "quality_score": 95.3,
  "quality_score_bid": 95.4,
  "quality_score_ask": 95.2,
  "calc_version": "rt_v4_bidask",
  "input_hash": "cfbdd848f95a28332bb60f70f4ae0e0363b2a7f061b3376c26573342d19415eb",
  "generated_at": "2026-03-22T10:36:15Z"
}
