{
  "pair": "USDT/CNY",
  "bid": 6.91029167,
  "ask": 6.93943243,
  "mid": 6.92486205,
  "asof_ts": 1773316307,
  "asof_iso": "2026-03-12T11:51:47Z",
  "timezone": "UTC",
  "source": "okx_p2p",
  "bid_source": "okx_p2p",
  "ask_source": "okx_p2p",
  "source_pool": [
    "okx_p2p"
  ],
  "source_count": 1,
  "sample_count": 144,
  "sample_count_bid": 144,
  "sample_count_ask": 148,
  "dispersion": 0.00043763,
  "dispersion_bid": 0.00031121,
  "dispersion_ask": 0.00056406,
  "quality_score": 95.3,
  "quality_score_bid": 95.2,
  "quality_score_ask": 95.4,
  "calc_version": "rt_v4_bidask",
  "input_hash": "412e94642bc33d49c77efae24467fbf32b46322c6c9f6a6232476fc7a463f016",
  "generated_at": "2026-03-12T11:51:47Z"
}
