{
  "pair": "USDT/CNY",
  "bid": 6.88904348,
  "ask": 6.97019868,
  "mid": 6.92962108,
  "asof_ts": 1773268449,
  "asof_iso": "2026-03-11T22:34:09Z",
  "timezone": "UTC",
  "source": "okx_p2p",
  "bid_source": "okx_p2p",
  "ask_source": "okx_p2p",
  "source_pool": [
    "okx_p2p"
  ],
  "source_count": 1,
  "sample_count": 138,
  "sample_count_bid": 138,
  "sample_count_ask": 151,
  "dispersion": 0.00240219,
  "dispersion_bid": 0.00208419,
  "dispersion_ask": 0.0027202,
  "quality_score": 94.7,
  "quality_score_bid": 94.2,
  "quality_score_ask": 95.2,
  "calc_version": "rt_v4_bidask",
  "input_hash": "3469f51533c6aae9c64c739365ffcca1c75df26047c750e9ed1ad63d38fe42a1",
  "generated_at": "2026-03-11T22:34:09Z"
}
