{
  "pair": "USDT/CNY",
  "bid": 6.92781818,
  "ask": 6.96983893,
  "mid": 6.94882855,
  "asof_ts": 1773877008,
  "asof_iso": "2026-03-18T23:36:48Z",
  "timezone": "UTC",
  "source": "okx_p2p",
  "bid_source": "okx_p2p",
  "ask_source": "okx_p2p",
  "source_pool": [
    "okx_p2p"
  ],
  "source_count": 1,
  "sample_count": 143,
  "sample_count_bid": 143,
  "sample_count_ask": 149,
  "dispersion": 0.00106747,
  "dispersion_bid": 0.0007547,
  "dispersion_ask": 0.00138024,
  "quality_score": 95.1,
  "quality_score_bid": 94.9,
  "quality_score_ask": 95.3,
  "calc_version": "rt_v4_bidask",
  "input_hash": "1ee158c9bb2ef9feb145dec10b8f1013c958c82cacaea4c1c4beca0a6fb40154",
  "generated_at": "2026-03-18T23:36:48Z"
}
