{
  "pair": "USDT/CNY",
  "bid": 6.81875168,
  "ask": 6.85125676,
  "mid": 6.83500422,
  "asof_ts": 1775822829,
  "asof_iso": "2026-04-10T12:07:09Z",
  "timezone": "UTC",
  "source": "okx_p2p",
  "bid_source": "okx_p2p",
  "ask_source": "okx_p2p",
  "source_pool": [
    "okx_p2p"
  ],
  "source_count": 1,
  "sample_count": 148,
  "sample_count_bid": 149,
  "sample_count_ask": 148,
  "dispersion": 0.00073233,
  "dispersion_bid": 0.00059529,
  "dispersion_ask": 0.00086937,
  "quality_score": 95.4,
  "quality_score_bid": 95.5,
  "quality_score_ask": 95.4,
  "calc_version": "rt_v4_bidask",
  "input_hash": "c9a0f095ef788cadb3dbf7cfa776d53ca91af0094e607e51e33075506c94c677",
  "generated_at": "2026-04-10T12:07:09Z"
}
