{
  "pair": "USDT/CNY",
  "bid": 6.91741667,
  "ask": 6.97016552,
  "mid": 6.94379109,
  "asof_ts": 1773770552,
  "asof_iso": "2026-03-17T18:02:32Z",
  "timezone": "UTC",
  "source": "okx_p2p",
  "bid_source": "okx_p2p",
  "ask_source": "okx_p2p",
  "source_pool": [
    "okx_p2p"
  ],
  "source_count": 1,
  "sample_count": 144,
  "sample_count_bid": 144,
  "sample_count_ask": 145,
  "dispersion": 0.00143224,
  "dispersion_bid": 0.00097353,
  "dispersion_ask": 0.00189094,
  "quality_score": 94.9,
  "quality_score_bid": 95.0,
  "quality_score_ask": 94.8,
  "calc_version": "rt_v4_bidask",
  "input_hash": "7369f7eb1e95114286d7e7119b9a992a377fe3e66896cf373182f465334c92dc",
  "generated_at": "2026-03-17T18:02:32Z"
}
