{
  "pair": "USDT/CNY",
  "bid": 6.92,
  "ask": 6.947625,
  "mid": 6.9338125,
  "asof_ts": 1773662731,
  "asof_iso": "2026-03-16T12:05:31Z",
  "timezone": "UTC",
  "source": "okx_p2p",
  "bid_source": "okx_p2p",
  "ask_source": "okx_p2p",
  "source_pool": [
    "okx_p2p"
  ],
  "source_count": 1,
  "sample_count": 143,
  "sample_count_bid": 143,
  "sample_count_ask": 144,
  "dispersion": 0.00035194,
  "dispersion_bid": 0.0,
  "dispersion_ask": 0.00070388,
  "quality_score": 95.0,
  "quality_score_bid": 95.0,
  "quality_score_ask": 95.0,
  "calc_version": "rt_v4_bidask",
  "input_hash": "da2299ab9f45f4542ef1f32b59d7838775c9be79488d3e6068803cc350e6a1e0",
  "generated_at": "2026-03-16T12:05:31Z"
}
