{
  "pair": "USDT/CNY",
  "bid": 6.91854054,
  "ask": 6.94289655,
  "mid": 6.93071855,
  "asof_ts": 1773648727,
  "asof_iso": "2026-03-16T08:12:07Z",
  "timezone": "UTC",
  "source": "okx_p2p",
  "bid_source": "okx_p2p",
  "ask_source": "okx_p2p",
  "source_pool": [
    "okx_p2p"
  ],
  "source_count": 1,
  "sample_count": 145,
  "sample_count_bid": 148,
  "sample_count_ask": 145,
  "dispersion": 0.00066993,
  "dispersion_bid": 0.00062013,
  "dispersion_ask": 0.00071973,
  "quality_score": 95.3,
  "quality_score_bid": 95.4,
  "quality_score_ask": 95.2,
  "calc_version": "rt_v4_bidask",
  "input_hash": "4e0e55031979fa8cbf6b28832716930b99f88f9dfbb4b88805383d0d9e62e16d",
  "generated_at": "2026-03-16T08:12:07Z"
}
