{
  "pair": "USDT/CNY",
  "bid": 6.79720833,
  "ask": 6.8884,
  "mid": 6.84280417,
  "asof_ts": 1777492845,
  "asof_iso": "2026-04-29T20:00:45Z",
  "timezone": "UTC",
  "source": "okx_p2p",
  "bid_source": "okx_p2p",
  "ask_source": "okx_p2p",
  "source_pool": [
    "okx_p2p"
  ],
  "source_count": 1,
  "sample_count": 144,
  "sample_count_bid": 144,
  "sample_count_ask": 150,
  "dispersion": 0.00298989,
  "dispersion_bid": 0.00143931,
  "dispersion_ask": 0.00454047,
  "quality_score": 94.8,
  "quality_score_bid": 94.8,
  "quality_score_ask": 94.7,
  "calc_version": "rt_v4_bidask",
  "input_hash": "cf555176217c87e7fb89d1b0fb88da31b693a1964c26f7a2120881f44a5b84ff",
  "generated_at": "2026-04-29T20:00:45Z"
}
