{
  "pair": "USDT/CNY",
  "bid": 6.8782973,
  "ask": 6.90255405,
  "mid": 6.89042568,
  "asof_ts": 1775626027,
  "asof_iso": "2026-04-08T05:27:07Z",
  "timezone": "UTC",
  "source": "okx_p2p",
  "bid_source": "okx_p2p",
  "ask_source": "okx_p2p",
  "source_pool": [
    "okx_p2p"
  ],
  "source_count": 1,
  "sample_count": 148,
  "sample_count_bid": 148,
  "sample_count_ask": 148,
  "dispersion": 0.0006966,
  "dispersion_bid": 0.00067688,
  "dispersion_ask": 0.00071632,
  "quality_score": 95.4,
  "quality_score_bid": 95.4,
  "quality_score_ask": 95.4,
  "calc_version": "rt_v4_bidask",
  "input_hash": "cc7e164f3dc26230c23535cea7de34de0e24229169ca30a1f99e0de8748ddd6e",
  "generated_at": "2026-04-08T05:27:07Z"
}
